icodeai_es/__init__.py
icodeai_es/base/__init__.py
icodeai_es/base/base_es.py
icodeai_es-0.0.0.dist-info/METADATA
icodeai_es-0.0.0.dist-info/WHEEL
icodeai_es-0.0.0.dist-info/top_level.txt
icodeai_es-0.0.0.dist-info/RECORD
