Metadata-Version: 2.1
Name: icodeai-es
Version: 0.0.0
Summary: Elastic Search
Home-page: https://icodeai.dev
Author: Allan Chepkoy
Author-email: allankiplangat22@gmail.com
Maintainer: Allan Chepkoy
Maintainer-email: allankiplangat22@gmail.com
License: MIT
Download-URL: https://pypi.org/project/icodeai_es
Platform: UNKNOWN
Requires-Dist: elasticsearch7
